fastapi_redis_dep/__init__.py
fastapi_redis_dep/cache.py
fastapi_redis_dep/client.py
fastapi_redis_dep/config.py
fastapi_redis_dep/exception.py
fastapi_redis_dep/redis.py
fastapi_redis_dep/utils/__init__.py
fastapi_redis_dep/utils/hash.py
fastapi_redis_dep/utils/list.py
fastapi_redis_dep/utils/set.py
fastapi_redis_dep/utils/string.py
fastapi_redis_dep/utils/zset.py
fastapi_redis_dep-0.3.3.dist-info/METADATA
fastapi_redis_dep-0.3.3.dist-info/WHEEL
fastapi_redis_dep-0.3.3.dist-info/RECORD
