Metadata-Version: 2.3
Name: fastapi-redis-dep
Version: 0.3.3
Summary: fastapi-redis-dep is a library that integrates Redis dependencies into FastAPI, making it easier to work with Redis in FastAPI.
Author: tiebingice
Requires-Python: >=3.11,<4.0
Classifier: Programming Language :: Python :: 3
Classifier: Programming Language :: Python :: 3.11
Classifier: Programming Language :: Python :: 3.12
Classifier: Programming Language :: Python :: 3.13
Requires-Dist: fastapi (>=0.115.6,<0.116.0)
Requires-Dist: orjson (>=3.10.14,<4.0.0)
Requires-Dist: pydantic-settings (>=2.7.0,<3.0.0)
Requires-Dist: redis-lock-py (>=1.1.1,<2.0.0)
Requires-Dist: redis[hiredis] (>=5.2.1,<6.0.0)
Requires-Dist: tenacity (>=8.3.0,<9.0.0)
Requires-Dist: uvicorn (>=0.34.0,<0.35.0)
